asconnect/__init__.py
asconnect/altool.py
asconnect/app_client.py
asconnect/app_info_client.py
asconnect/beta_review_client.py
asconnect/build_client.py
asconnect/client.py
asconnect/exceptions.py
asconnect/httpclient.py
asconnect/models/__init__.py
asconnect/models/app_info.py
asconnect/models/app_store.py
asconnect/models/app_store_version_localizations.py
asconnect/models/apps.py
asconnect/models/beta_app_review.py
asconnect/models/beta_detail.py
asconnect/models/beta_groups.py
asconnect/models/builds.py
asconnect/models/common.py
asconnect/models/idfa.py
asconnect/models/localization.py
asconnect/models/reviews.py
asconnect/models/screenshots.py
asconnect/models/users.py
asconnect/reviews_client.py
asconnect/screenshot_client.py
asconnect/sorting.py
asconnect/users_client.py
asconnect/utilities.py
asconnect/version_client.py
asconnect-7.0.1.dist-info/LICENSE
asconnect-7.0.1.dist-info/METADATA
asconnect-7.0.1.dist-info/WHEEL
asconnect-7.0.1.dist-info/RECORD
