Metadata-Version: 2.1
Name: asconnect
Version: 7.0.1
Summary: A wrapper around the Apple App Store Connect APIs
Home-page: https://github.com/microsoft/asconnect
License: MIT
Keywords: apple,app store,itunes,connect
Author: Dale Myers
Author-email: dalemyers@microsoft.com
Requires-Python: >=3.11,<4.0
Classifier: Development Status :: 5 - Production/Stable
Classifier: Environment :: Console
Classifier: Environment :: MacOS X
Classifier: Intended Audience :: Developers
Classifier: License :: OSI Approved :: MIT License
Classifier: Programming Language :: Python :: 3
Classifier: Programming Language :: Python :: 3.11
Classifier: Programming Language :: Python :: 3.12
Classifier: Programming Language :: Python :: 3.13
Classifier: Topic :: Software Development
Classifier: Topic :: Utilities
Requires-Dist: cryptography (>=40,<46)
Requires-Dist: deserialize (>=2.0.1,<3.0.0)
Requires-Dist: pyjwt (>=2.6.0,<3.0.0)
Requires-Dist: requests (>=2.28.2,<3.0.0)
Requires-Dist: tenacity (>=8.2.2,<9.0.0)
Project-URL: Repository, https://github.com/microsoft/asconnect
